langchain_memvid/__init__.py
langchain_memvid/config.py
langchain_memvid/encoder.py
langchain_memvid/exceptions.py
langchain_memvid/index.py
langchain_memvid/logging.py
langchain_memvid/retriever.py
langchain_memvid/types.py
langchain_memvid/vectorstore.py
langchain_memvid/utils/__init__.py
langchain_memvid/utils/metadata.py
langchain_memvid/utils/progress.py
langchain_memvid/video/__init__.py
langchain_memvid/video/codecs.py
langchain_memvid/video/default.py
langchain_memvid/video/ffmpeg.py
langchain_memvid-0.1.10.dist-info/licenses/LICENSE
langchain_memvid-0.1.10.dist-info/licenses/LICENSES.md
langchain_memvid-0.1.10.dist-info/METADATA
langchain_memvid-0.1.10.dist-info/WHEEL
langchain_memvid-0.1.10.dist-info/top_level.txt
langchain_memvid-0.1.10.dist-info/RECORD
