Metadata-Version: 2.4
Name: langchain-memvid
Version: 0.1.10
Summary: LangChain implementation for MemVid (video-based vector storage)
Author-email: Dawid Ciepiela <71898979+sarumaj@users.noreply.github.com>
License: BSD-3-Clause
Project-URL: repository, https://github.com/sarumaj/langchain-memvid
Classifier: Programming Language :: Python :: 3.12
Classifier: License :: OSI Approved :: BSD License
Classifier: Operating System :: OS Independent
Requires-Python: >=3.12
License-File: LICENSE
License-File: LICENSES.md
Requires-Dist: faiss-cpu==1.13.2
Requires-Dist: langchain-core==1.2.5
Requires-Dist: nest_asyncio==1.6.0
Requires-Dist: qrcode[pil]==8.2
Requires-Dist: opencv-contrib-python==4.12.0.88
Requires-Dist: orjson==3.11.5
Requires-Dist: pydantic==2.12.5
Requires-Dist: tqdm==4.67.1
Provides-Extra: test
Requires-Dist: pytest==9.0.2; extra == "test"
Requires-Dist: pytest-asyncio==1.3.0; extra == "test"
Requires-Dist: pytest-benchmark==5.2.3; extra == "test"
Provides-Extra: docs
Requires-Dist: sphinx<9.0.0; extra == "docs"
Requires-Dist: sphinx-rtd-theme==3.0.2; extra == "docs"
Requires-Dist: sphinx-autodoc-typehints<3.6.0; extra == "docs"
Requires-Dist: myst-parser==4.0.1; extra == "docs"
Requires-Dist: tomli==2.3.0; extra == "docs"
Dynamic: license-file
